[
	{
		"id": "1",
        "caption": "Come on, find that damn key!",
        "label": "",
        "emmiter": "Ghost",
        "require": "",
        "nextUnlocked": "2",
        "nextLocked": "",
        "trigger": "",
        "pickable": false,
		"important": true
	},
	{
		"id": "2",
        "caption": "We don't have much time left!",
        "label": "",
        "emmiter": "Player",
        "require": "",
        "nextUnlocked": "3",
        "nextLocked": "",
        "trigger": "",
        "pickable": false,
		"important": true
	},
	{
		"id": "3",
        "caption": "Do tou want me to repeat?",
        "label": "",
        "emmiter": "Ghost",
        "require": "",
        "nextUnlocked": "",
        "nextLocked": "",
        "trigger": "",
        "pickable": false,
		"important": true,
		"haveChoice": true,
		"choice1": "Yes",
		"choice2": "No",
		"nextChoice1": "1",
		"nextChoice2": ""
	}
]